{
  "data": {
    "article": {},
    "attachments": {},
    "author_id": "1684788633797287936",
    "context_annotations": [
      {
        "domain": {
          "description": "Top level entities that describe a Brands industry",
          "id": "45",
          "name": "Brand Vertical"
        },
        "entity": {
          "id": "781974597226799105",
          "name": "B2B"
        }
      },
      {
        "domain": {
          "description": "Entity Service top level domain, every item that is in Entity Service should be in this domain",
          "id": "30",
          "name": "Entities [Entity Service]"
        },
        "entity": {
          "id": "781974597172203520",
          "name": "Services - B2B"
        }
      },
      {
        "domain": {
          "description": "Brands and Companies",
          "id": "47",
          "name": "Brand"
        },
        "entity": {
          "id": "10029202046",
          "name": "Huawei"
        }
      },
      {
        "domain": {
          "description": "A taxonomy of user interests. ",
          "id": "131",
          "name": "Unified Twitter Taxonomy"
        },
        "entity": {
          "id": "10029202046",
          "name": "Huawei"
        }
      }
    ],
    "conversation_id": "1953633295788650522",
    "created_at": "2025-08-08T01:44:09.000Z",
    "edit_controls": {
      "editable_until": "2025-08-08T02:44:09.000Z",
      "edits_remaining": 5,
      "is_edit_eligible": false
    },
    "edit_history_tweet_ids": [
      "1953633295788650522"
    ],
    "entities": {
      "mentions": [
        {
          "end": 19,
          "id": "1794617194954850304",
          "start": 3,
          "username": "Baixiaoming0707"
        }
      ]
    },
    "geo": {},
    "id": "1953633295788650522",
    "lang": "zh",
    "note_tweet": {
      "entities": {}
    },
    "possibly_sensitive": false,
    "public_metrics": {
      "bookmark_count": 0,
      "impression_count": 0,
      "like_count": 0,
      "quote_count": 0,
      "reply_count": 0,
      "retweet_count": 1
    },
    "referenced_tweets": [
      {
        "id": "1953629313829388308",
        "type": "retweeted"
      }
    ],
    "reply_settings": "everyone",
    "text": "RT @Baixiaoming0707: 美国最有名的手机品牌是苹果\n中国最有名的手机品牌是华为和小米\n韩国最有名的手机品牌是三星\n日本最有名的手机品牌是？\n其他国家还有哪些有名的手机品牌？"
  },
  "includes": {
    "tweets": [
      {
        "article": {},
        "attachments": {},
        "author_id": "1684788633797287936",
        "context_annotations": [
          {
            "domain": {
              "description": "Top level entities that describe a Brands industry",
              "id": "45",
              "name": "Brand Vertical"
            },
            "entity": {
              "id": "781974597226799105",
              "name": "B2B"
            }
          },
          {
            "domain": {
              "description": "Entity Service top level domain, every item that is in Entity Service should be in this domain",
              "id": "30",
              "name": "Entities [Entity Service]"
            },
            "entity": {
              "id": "781974597172203520",
              "name": "Services - B2B"
            }
          },
          {
            "domain": {
              "description": "Brands and Companies",
              "id": "47",
              "name": "Brand"
            },
            "entity": {
              "id": "10029202046",
              "name": "Huawei"
            }
          },
          {
            "domain": {
              "description": "A taxonomy of user interests. ",
              "id": "131",
              "name": "Unified Twitter Taxonomy"
            },
            "entity": {
              "id": "10029202046",
              "name": "Huawei"
            }
          }
        ],
        "conversation_id": "1953633295788650522",
        "created_at": "2025-08-08T01:44:09.000Z",
        "edit_controls": {
          "editable_until": "2025-08-08T02:44:09.000Z",
          "edits_remaining": 5,
          "is_edit_eligible": false
        },
        "edit_history_tweet_ids": [
          "1953633295788650522"
        ],
        "entities": {
          "mentions": [
            {
              "end": 19,
              "id": "1794617194954850304",
              "start": 3,
              "username": "Baixiaoming0707"
            }
          ]
        },
        "geo": {},
        "id": "1953633295788650522",
        "lang": "zh",
        "note_tweet": {
          "entities": {}
        },
        "possibly_sensitive": false,
        "public_metrics": {
          "bookmark_count": 0,
          "impression_count": 0,
          "like_count": 0,
          "quote_count": 0,
          "reply_count": 0,
          "retweet_count": 1
        },
        "referenced_tweets": [
          {
            "id": "1953629313829388308",
            "type": "retweeted"
          }
        ],
        "reply_settings": "everyone",
        "text": "RT @Baixiaoming0707: 美国最有名的手机品牌是苹果\n中国最有名的手机品牌是华为和小米\n韩国最有名的手机品牌是三星\n日本最有名的手机品牌是？\n其他国家还有哪些有名的手机品牌？"
      },
      {
        "article": {},
        "attachments": {},
        "author_id": "1794617194954850304",
        "context_annotations": [
          {
            "domain": {
              "description": "Top level entities that describe a Brands industry",
              "id": "45",
              "name": "Brand Vertical"
            },
            "entity": {
              "id": "781974597226799105",
              "name": "B2B"
            }
          },
          {
            "domain": {
              "description": "Entity Service top level domain, every item that is in Entity Service should be in this domain",
              "id": "30",
              "name": "Entities [Entity Service]"
            },
            "entity": {
              "id": "781974597172203520",
              "name": "Services - B2B"
            }
          },
          {
            "domain": {
              "description": "Brands and Companies",
              "id": "47",
              "name": "Brand"
            },
            "entity": {
              "id": "10029202046",
              "name": "Huawei"
            }
          },
          {
            "domain": {
              "description": "A taxonomy of user interests. ",
              "id": "131",
              "name": "Unified Twitter Taxonomy"
            },
            "entity": {
              "id": "10029202046",
              "name": "Huawei"
            }
          }
        ],
        "conversation_id": "1953629313829388308",
        "created_at": "2025-08-08T01:28:19.000Z",
        "edit_controls": {
          "editable_until": "2025-08-08T02:28:19.000Z",
          "edits_remaining": 5,
          "is_edit_eligible": true
        },
        "edit_history_tweet_ids": [
          "1953629313829388308"
        ],
        "entities": {},
        "geo": {},
        "id": "1953629313829388308",
        "lang": "zh",
        "note_tweet": {
          "entities": {}
        },
        "possibly_sensitive": false,
        "public_metrics": {
          "bookmark_count": 0,
          "impression_count": 90,
          "like_count": 5,
          "quote_count": 0,
          "reply_count": 2,
          "retweet_count": 1
        },
        "reply_settings": "everyone",
        "text": "美国最有名的手机品牌是苹果\n中国最有名的手机品牌是华为和小米\n韩国最有名的手机品牌是三星\n日本最有名的手机品牌是？\n其他国家还有哪些有名的手机品牌？"
      }
    ],
    "users": [
      {
        "created_at": "2023-07-28T04:51:35.000Z",
        "description": "🌌 | 🩷🩵🏳️‍⚧️ | mtf | 家长反对所以暂时无证不含糖 | 跨跨帮助跨跨 | 挚爱 @Sakura_mo_yu",
        "entities": {
          "description": {
            "mentions": [
              {
                "end": 61,
                "start": 48,
                "username": "Sakura_mo_yu"
              }
            ]
          },
          "url": {
            "urls": [
              {
                "display_url": "x.com/Muoujiang__?t=…",
                "end": 23,
                "expanded_url": "https://x.com/Muoujiang__?t=wksvJV8Eba0OwfH6Jb0FWw&s=09",
                "start": 0,
                "url": "https://t.co/gWovYpoBzT"
              }
            ]
          }
        },
        "id": "1684788633797287936",
        "location": "雌二醇星球驻🌏大使馆",
        "name": "🧊沫柠～🍋🍥",
        "pinned_tweet_id": "1927365238833250356",
        "profile_image_url": "https://pbs.twimg.com/profile_images/1944698823730700289/9KodktqH_normal.jpg",
        "protected": false,
        "public_metrics": {
          "followers_count": 21843,
          "following_count": 10890,
          "like_count": 81967,
          "listed_count": 77,
          "media_count": 4005,
          "tweet_count": 14883
        },
        "url": "https://t.co/gWovYpoBzT",
        "username": "Moningmeng",
        "verified": false
      },
      {
        "created_at": "2024-05-26T06:31:28.000Z",
        "description": "08年广西土著 | 简中/正體/English | 政史地亡命文科生 | 快品尝国宾酒尊尼获加 | 都去关注@virtual_kaf ！ | 永远追随国王→@oldsddl4gunmu @diangunottosm @otto_houguoyu | 抖音:29289785213",
        "entities": {
          "description": {
            "mentions": [
              {
                "end": 66,
                "start": 54,
                "username": "virtual_kaf"
              },
              {
                "end": 92,
                "start": 78,
                "username": "oldsddl4gunmu"
              },
              {
                "end": 107,
                "start": 93,
                "username": "diangunottosm"
              },
              {
                "end": 122,
                "start": 108,
                "username": "otto_houguoyu"
              }
            ]
          }
        },
        "id": "1794617194954850304",
        "location": "无处不在 无影无踪",
        "name": "白小铭",
        "pinned_tweet_id": "1948552894451777645",
        "profile_image_url": "https://pbs.twimg.com/profile_images/1923928431512707072/VKPjgBRW_normal.jpg",
        "protected": false,
        "public_metrics": {
          "followers_count": 1125,
          "following_count": 1017,
          "like_count": 12594,
          "listed_count": 4,
          "media_count": 660,
          "tweet_count": 3945
        },
        "username": "Baixiaoming0707",
        "verified": false
      }
    ]
  }
}