{
  "data": {
    "article": {},
    "attachments": {
      "media_keys": [
        "3_1952666049884856320",
        "3_1952666050082050048"
      ],
      "media_source_tweet_id": [
        "1952666065470665143",
        "1952666065470665143"
      ]
    },
    "author_id": "1684788633797287936",
    "conversation_id": "1952914263984468013",
    "created_at": "2025-08-06T02:06:58.000Z",
    "edit_controls": {
      "editable_until": "2025-08-06T03:06:58.000Z",
      "edits_remaining": 5,
      "is_edit_eligible": false
    },
    "edit_history_tweet_ids": [
      "1952914263984468013"
    ],
    "entities": {
      "mentions": [
        {
          "end": 12,
          "id": "1246457571407302656",
          "start": 3,
          "username": "Gril_iar"
        }
      ],
      "urls": [
        {
          "display_url": "pic.x.com/z3ZwRp6deI",
          "end": 43,
          "expanded_url": "https://x.com/Gril_iar/status/1952666065470665143/photo/1",
          "media_key": "3_1952666049884856320",
          "start": 20,
          "url": "https://t.co/z3ZwRp6deI"
        },
        {
          "display_url": "pic.x.com/z3ZwRp6deI",
          "end": 43,
          "expanded_url": "https://x.com/Gril_iar/status/1952666065470665143/photo/1",
          "media_key": "3_1952666050082050048",
          "start": 20,
          "url": "https://t.co/z3ZwRp6deI"
        }
      ]
    },
    "geo": {},
    "id": "1952914263984468013",
    "lang": "zh",
    "note_tweet": {
      "entities": {}
    },
    "possibly_sensitive": false,
    "public_metrics": {
      "bookmark_count": 0,
      "impression_count": 0,
      "like_count": 0,
      "quote_count": 0,
      "reply_count": 0,
      "retweet_count": 3
    },
    "referenced_tweets": [
      {
        "id": "1952666065470665143",
        "type": "retweeted"
      }
    ],
    "reply_settings": "everyone",
    "text": "RT @Gril_iar: 阴暗的站街 https://t.co/z3ZwRp6deI"
  },
  "includes": {
    "media": [
      {
        "height": 2048,
        "media_key": "3_1952666049884856320",
        "public_metrics": {},
        "type": "photo",
        "url": "https://pbs.twimg.com/media/GxlDbTxaIAAusNC.jpg",
        "width": 1535
      },
      {
        "height": 2048,
        "media_key": "3_1952666050082050048",
        "public_metrics": {},
        "type": "photo",
        "url": "https://pbs.twimg.com/media/GxlDbUgbEAA1-NS.jpg",
        "width": 1536
      }
    ],
    "tweets": [
      {
        "article": {},
        "attachments": {
          "media_keys": [
            "3_1952666049884856320",
            "3_1952666050082050048"
          ],
          "media_source_tweet_id": [
            "1952666065470665143",
            "1952666065470665143"
          ]
        },
        "author_id": "1684788633797287936",
        "conversation_id": "1952914263984468013",
        "created_at": "2025-08-06T02:06:58.000Z",
        "edit_controls": {
          "editable_until": "2025-08-06T03:06:58.000Z",
          "edits_remaining": 5,
          "is_edit_eligible": false
        },
        "edit_history_tweet_ids": [
          "1952914263984468013"
        ],
        "entities": {
          "mentions": [
            {
              "end": 12,
              "id": "1246457571407302656",
              "start": 3,
              "username": "Gril_iar"
            }
          ],
          "urls": [
            {
              "display_url": "pic.x.com/z3ZwRp6deI",
              "end": 43,
              "expanded_url": "https://x.com/Gril_iar/status/1952666065470665143/photo/1",
              "media_key": "3_1952666049884856320",
              "start": 20,
              "url": "https://t.co/z3ZwRp6deI"
            },
            {
              "display_url": "pic.x.com/z3ZwRp6deI",
              "end": 43,
              "expanded_url": "https://x.com/Gril_iar/status/1952666065470665143/photo/1",
              "media_key": "3_1952666050082050048",
              "start": 20,
              "url": "https://t.co/z3ZwRp6deI"
            }
          ]
        },
        "geo": {},
        "id": "1952914263984468013",
        "lang": "zh",
        "note_tweet": {
          "entities": {}
        },
        "possibly_sensitive": false,
        "public_metrics": {
          "bookmark_count": 0,
          "impression_count": 0,
          "like_count": 0,
          "quote_count": 0,
          "reply_count": 0,
          "retweet_count": 3
        },
        "referenced_tweets": [
          {
            "id": "1952666065470665143",
            "type": "retweeted"
          }
        ],
        "reply_settings": "everyone",
        "text": "RT @Gril_iar: 阴暗的站街 https://t.co/z3ZwRp6deI"
      },
      {
        "article": {},
        "attachments": {
          "media_keys": [
            "3_1952666049884856320",
            "3_1952666050082050048"
          ]
        },
        "author_id": "1246457571407302656",
        "conversation_id": "1952666065470665143",
        "created_at": "2025-08-05T09:40:43.000Z",
        "edit_controls": {
          "editable_until": "2025-08-05T10:40:43.000Z",
          "edits_remaining": 5,
          "is_edit_eligible": true
        },
        "edit_history_tweet_ids": [
          "1952666065470665143"
        ],
        "entities": {
          "urls": [
            {
              "display_url": "pic.x.com/z3ZwRp6deI",
              "end": 29,
              "expanded_url": "https://x.com/Gril_iar/status/1952666065470665143/photo/1",
              "media_key": "3_1952666049884856320",
              "start": 6,
              "url": "https://t.co/z3ZwRp6deI"
            },
            {
              "display_url": "pic.x.com/z3ZwRp6deI",
              "end": 29,
              "expanded_url": "https://x.com/Gril_iar/status/1952666065470665143/photo/1",
              "media_key": "3_1952666050082050048",
              "start": 6,
              "url": "https://t.co/z3ZwRp6deI"
            }
          ]
        },
        "geo": {},
        "id": "1952666065470665143",
        "lang": "zh",
        "note_tweet": {
          "entities": {}
        },
        "possibly_sensitive": false,
        "public_metrics": {
          "bookmark_count": 13,
          "impression_count": 28178,
          "like_count": 294,
          "quote_count": 0,
          "reply_count": 22,
          "retweet_count": 3
        },
        "reply_settings": "everyone",
        "text": "阴暗的站街 https://t.co/z3ZwRp6deI"
      }
    ],
    "users": [
      {
        "created_at": "2023-07-28T04:51:35.000Z",
        "description": "🌌 | 🩷🩵🏳️‍⚧️ | mtf | 家长反对所以暂时无证不含糖 | 跨跨帮助跨跨 | 挚爱 @Sakura_mo_yu",
        "entities": {
          "description": {
            "mentions": [
              {
                "end": 61,
                "start": 48,
                "username": "Sakura_mo_yu"
              }
            ]
          },
          "url": {
            "urls": [
              {
                "display_url": "x.com/Muoujiang__?t=…",
                "end": 23,
                "expanded_url": "https://x.com/Muoujiang__?t=wksvJV8Eba0OwfH6Jb0FWw&s=09",
                "start": 0,
                "url": "https://t.co/gWovYpoBzT"
              }
            ]
          }
        },
        "id": "1684788633797287936",
        "location": "雌二醇星球驻🌏大使馆",
        "name": "🧊沫柠～🍋🍥",
        "pinned_tweet_id": "1927365238833250356",
        "profile_image_url": "https://pbs.twimg.com/profile_images/1944698823730700289/9KodktqH_normal.jpg",
        "protected": false,
        "public_metrics": {
          "followers_count": 21787,
          "following_count": 10876,
          "like_count": 81705,
          "listed_count": 77,
          "media_count": 3992,
          "tweet_count": 14796
        },
        "url": "https://t.co/gWovYpoBzT",
        "username": "Moningmeng",
        "verified": false
      },
      {
        "created_at": "2020-04-04T15:20:27.000Z",
        "description": "愿逐月华流照君",
        "id": "1246457571407302656",
        "location": "Xi'an",
        "name": "🌰🐢",
        "pinned_tweet_id": "1890068642840387702",
        "profile_image_url": "https://pbs.twimg.com/profile_images/1815795023918817280/1GGReWdM_normal.jpg",
        "protected": false,
        "public_metrics": {
          "followers_count": 2469,
          "following_count": 526,
          "like_count": 10264,
          "listed_count": 5,
          "media_count": 407,
          "tweet_count": 4714
        },
        "username": "Gril_iar",
        "verified": false
      }
    ]
  }
}