{
  "data": {
    "article": {},
    "attachments": {
      "media_keys": [
        "3_1935958514674839552",
        "3_1935958514922409984",
        "3_1935958512846475264"
      ],
      "media_source_tweet_id": [
        "1935958518303277378",
        "1935958518303277378",
        "1935958518303277378"
      ]
    },
    "author_id": "1684788633797287936",
    "context_annotations": [
      {
        "domain": {
          "description": "Categories within Brand Verticals that narrow down the scope of Brands",
          "id": "46",
          "name": "Business Taxonomy"
        },
        "entity": {
          "description": "Brands, companies, advertisers and every non-person handle with the profit intent related to offline and online games such as gaming consoles, tabletop games, video game publishers",
          "id": "1557696940178935808",
          "name": "Gaming Business"
        }
      }
    ],
    "conversation_id": "1936247397690347569",
    "created_at": "2025-06-21T02:18:48.000Z",
    "edit_controls": {
      "editable_until": "2025-06-21T03:18:48.000Z",
      "edits_remaining": 5,
      "is_edit_eligible": false
    },
    "edit_history_tweet_ids": [
      "1936247397690347569"
    ],
    "entities": {
      "mentions": [
        {
          "end": 13,
          "id": "1892197607109476352",
          "start": 3,
          "username": "lianshufa"
        }
      ],
      "urls": [
        {
          "display_url": "pic.x.com/ojUbUnBVCJ",
          "end": 84,
          "expanded_url": "https://x.com/lianshufa/status/1935958518303277378/photo/1",
          "media_key": "3_1935958514674839552",
          "start": 61,
          "url": "https://t.co/ojUbUnBVCJ"
        },
        {
          "display_url": "pic.x.com/ojUbUnBVCJ",
          "end": 84,
          "expanded_url": "https://x.com/lianshufa/status/1935958518303277378/photo/1",
          "media_key": "3_1935958514922409984",
          "start": 61,
          "url": "https://t.co/ojUbUnBVCJ"
        },
        {
          "display_url": "pic.x.com/ojUbUnBVCJ",
          "end": 84,
          "expanded_url": "https://x.com/lianshufa/status/1935958518303277378/photo/1",
          "media_key": "3_1935958512846475264",
          "start": 61,
          "url": "https://t.co/ojUbUnBVCJ"
        }
      ]
    },
    "geo": {},
    "id": "1936247397690347569",
    "lang": "zh",
    "note_tweet": {
      "entities": {}
    },
    "possibly_sensitive": false,
    "public_metrics": {
      "bookmark_count": 0,
      "impression_count": 0,
      "like_count": 0,
      "quote_count": 0,
      "reply_count": 0,
      "retweet_count": 3
    },
    "referenced_tweets": [
      {
        "id": "1935958518303277378",
        "type": "retweeted"
      }
    ],
    "reply_settings": "everyone",
    "text": "RT @lianshufa: 今天我们初三在学校最后一天了，我们在班里合影，在后黑板上签名。我在后黑板的右下角留了个跨旗 https://t.co/ojUbUnBVCJ"
  },
  "includes": {
    "media": [
      {
        "height": 1536,
        "media_key": "3_1935958514674839552",
        "public_metrics": {},
        "type": "photo",
        "url": "https://pbs.twimg.com/media/Gt3oAw8WMAAqCzs.jpg",
        "width": 2048
      },
      {
        "height": 1536,
        "media_key": "3_1935958514922409984",
        "public_metrics": {},
        "type": "photo",
        "url": "https://pbs.twimg.com/media/Gt3oAx3X0AAPTP9.jpg",
        "width": 2048
      },
      {
        "height": 1192,
        "media_key": "3_1935958512846475264",
        "public_metrics": {},
        "type": "photo",
        "url": "https://pbs.twimg.com/media/Gt3oAqIbkAAh6xk.jpg",
        "width": 2216
      }
    ],
    "tweets": [
      {
        "article": {},
        "attachments": {
          "media_keys": [
            "3_1935958514674839552",
            "3_1935958514922409984",
            "3_1935958512846475264"
          ],
          "media_source_tweet_id": [
            "1935958518303277378",
            "1935958518303277378",
            "1935958518303277378"
          ]
        },
        "author_id": "1684788633797287936",
        "context_annotations": [
          {
            "domain": {
              "description": "Categories within Brand Verticals that narrow down the scope of Brands",
              "id": "46",
              "name": "Business Taxonomy"
            },
            "entity": {
              "description": "Brands, companies, advertisers and every non-person handle with the profit intent related to offline and online games such as gaming consoles, tabletop games, video game publishers",
              "id": "1557696940178935808",
              "name": "Gaming Business"
            }
          }
        ],
        "conversation_id": "1936247397690347569",
        "created_at": "2025-06-21T02:18:48.000Z",
        "edit_controls": {
          "editable_until": "2025-06-21T03:18:48.000Z",
          "edits_remaining": 5,
          "is_edit_eligible": false
        },
        "edit_history_tweet_ids": [
          "1936247397690347569"
        ],
        "entities": {
          "mentions": [
            {
              "end": 13,
              "id": "1892197607109476352",
              "start": 3,
              "username": "lianshufa"
            }
          ],
          "urls": [
            {
              "display_url": "pic.x.com/ojUbUnBVCJ",
              "end": 84,
              "expanded_url": "https://x.com/lianshufa/status/1935958518303277378/photo/1",
              "media_key": "3_1935958514674839552",
              "start": 61,
              "url": "https://t.co/ojUbUnBVCJ"
            },
            {
              "display_url": "pic.x.com/ojUbUnBVCJ",
              "end": 84,
              "expanded_url": "https://x.com/lianshufa/status/1935958518303277378/photo/1",
              "media_key": "3_1935958514922409984",
              "start": 61,
              "url": "https://t.co/ojUbUnBVCJ"
            },
            {
              "display_url": "pic.x.com/ojUbUnBVCJ",
              "end": 84,
              "expanded_url": "https://x.com/lianshufa/status/1935958518303277378/photo/1",
              "media_key": "3_1935958512846475264",
              "start": 61,
              "url": "https://t.co/ojUbUnBVCJ"
            }
          ]
        },
        "geo": {},
        "id": "1936247397690347569",
        "lang": "zh",
        "note_tweet": {
          "entities": {}
        },
        "possibly_sensitive": false,
        "public_metrics": {
          "bookmark_count": 0,
          "impression_count": 0,
          "like_count": 0,
          "quote_count": 0,
          "reply_count": 0,
          "retweet_count": 3
        },
        "referenced_tweets": [
          {
            "id": "1935958518303277378",
            "type": "retweeted"
          }
        ],
        "reply_settings": "everyone",
        "text": "RT @lianshufa: 今天我们初三在学校最后一天了，我们在班里合影，在后黑板上签名。我在后黑板的右下角留了个跨旗 https://t.co/ojUbUnBVCJ"
      },
      {
        "article": {},
        "attachments": {
          "media_keys": [
            "3_1935958514674839552",
            "3_1935958514922409984",
            "3_1935958512846475264"
          ]
        },
        "author_id": "1892197607109476352",
        "context_annotations": [
          {
            "domain": {
              "description": "Categories within Brand Verticals that narrow down the scope of Brands",
              "id": "46",
              "name": "Business Taxonomy"
            },
            "entity": {
              "description": "Brands, companies, advertisers and every non-person handle with the profit intent related to offline and online games such as gaming consoles, tabletop games, video game publishers",
              "id": "1557696940178935808",
              "name": "Gaming Business"
            }
          }
        ],
        "conversation_id": "1935958518303277378",
        "created_at": "2025-06-20T07:10:53.000Z",
        "edit_controls": {
          "editable_until": "2025-06-20T08:10:53.000Z",
          "edits_remaining": 5,
          "is_edit_eligible": true
        },
        "edit_history_tweet_ids": [
          "1935958518303277378"
        ],
        "entities": {
          "urls": [
            {
              "display_url": "pic.x.com/ojUbUnBVCJ",
              "end": 69,
              "expanded_url": "https://x.com/lianshufa/status/1935958518303277378/photo/1",
              "media_key": "3_1935958514674839552",
              "start": 46,
              "url": "https://t.co/ojUbUnBVCJ"
            },
            {
              "display_url": "pic.x.com/ojUbUnBVCJ",
              "end": 69,
              "expanded_url": "https://x.com/lianshufa/status/1935958518303277378/photo/1",
              "media_key": "3_1935958514922409984",
              "start": 46,
              "url": "https://t.co/ojUbUnBVCJ"
            },
            {
              "display_url": "pic.x.com/ojUbUnBVCJ",
              "end": 69,
              "expanded_url": "https://x.com/lianshufa/status/1935958518303277378/photo/1",
              "media_key": "3_1935958512846475264",
              "start": 46,
              "url": "https://t.co/ojUbUnBVCJ"
            }
          ]
        },
        "geo": {},
        "id": "1935958518303277378",
        "lang": "zh",
        "note_tweet": {
          "entities": {}
        },
        "possibly_sensitive": false,
        "public_metrics": {
          "bookmark_count": 2,
          "impression_count": 7765,
          "like_count": 116,
          "quote_count": 0,
          "reply_count": 7,
          "retweet_count": 3
        },
        "reply_settings": "everyone",
        "text": "今天我们初三在学校最后一天了，我们在班里合影，在后黑板上签名。我在后黑板的右下角留了个跨旗 https://t.co/ojUbUnBVCJ"
      }
    ],
    "users": [
      {
        "created_at": "2023-07-28T04:51:35.000Z",
        "description": "🌌 | 🩷🩵🏳️‍⚧️ | 萌新木桶饭 | 家长反对党 | 在留头发 | HRT→大学之后🍥（怕被家里发现 | 跨跨帮助跨跨 | 老婆 @Sakura_mo_yu | 最好的姐妹 @wflmyblj @Livedeath750122",
        "entities": {
          "description": {
            "mentions": [
              {
                "end": 81,
                "start": 68,
                "username": "Sakura_mo_yu"
              },
              {
                "end": 99,
                "start": 90,
                "username": "wflmyblj"
              },
              {
                "end": 116,
                "start": 100,
                "username": "Livedeath750122"
              }
            ]
          },
          "url": {
            "urls": [
              {
                "display_url": "x.com/Muoujiang__?t=…",
                "end": 23,
                "expanded_url": "https://x.com/Muoujiang__?t=wksvJV8Eba0OwfH6Jb0FWw&s=09",
                "start": 0,
                "url": "https://t.co/gWovYpoBzT"
              }
            ]
          }
        },
        "id": "1684788633797287936",
        "location": "Nod-Krai, Snezhnaya",
        "name": "沫柠～🍋🍈🍋‍🟩🫐🍏🍇🍧🍡🧁🍭🧊🍩🧃🍬🍞🍨🧇🍟🍥🏳️‍⚧️",
        "pinned_tweet_id": "1936012677018743134",
        "profile_image_url": "https://pbs.twimg.com/profile_images/1932569658647064579/Q1muwosh_normal.jpg",
        "protected": false,
        "public_metrics": {
          "followers_count": 21408,
          "following_count": 10711,
          "like_count": 77300,
          "listed_count": 76,
          "media_count": 3757,
          "tweet_count": 13763
        },
        "url": "https://t.co/gWovYpoBzT",
        "username": "Moningmeng",
        "verified": false
      },
      {
        "created_at": "2025-02-19T13:01:39.000Z",
        "description": "电吉他🎸｜MtF🏳️‍🌈🏳️‍⚧️｜半个家长党+家暴党｜无证含糖｜HRT since 2025.06.19｜主营B站，推特，QQ｜精神有时不正常，不od，不割手，无双相",
        "id": "1892197607109476352",
        "location": "中国 香港",
        "name": "lsf~(C₂₃H₃₂🍥₃)🏳️‍⚧️",
        "pinned_tweet_id": "1935501094240797064",
        "profile_image_url": "https://pbs.twimg.com/profile_images/1934257579573809152/pZaO8uF0_normal.jpg",
        "protected": false,
        "public_metrics": {
          "followers_count": 455,
          "following_count": 1338,
          "like_count": 97,
          "listed_count": 0,
          "media_count": 17,
          "tweet_count": 130
        },
        "username": "lianshufa",
        "verified": false
      }
    ]
  }
}