{
  "data": {
    "article": {},
    "attachments": {},
    "author_id": "1684788633797287936",
    "conversation_id": "2019596504005333156",
    "created_at": "2026-02-06T02:18:23.000Z",
    "edit_controls": {
      "editable_until": "2026-02-06T03:18:23.000Z",
      "edits_remaining": 5,
      "is_edit_eligible": false
    },
    "edit_history_tweet_ids": [
      "2019596504005333156"
    ],
    "entities": {
      "mentions": [
        {
          "end": 14,
          "id": "1935176310663401472",
          "start": 3,
          "username": "S_Hyoscine"
        }
      ]
    },
    "geo": {},
    "id": "2019596504005333156",
    "lang": "zh",
    "note_tweet": {
      "entities": {}
    },
    "possibly_sensitive": false,
    "public_metrics": {
      "bookmark_count": 0,
      "impression_count": 0,
      "like_count": 0,
      "quote_count": 0,
      "reply_count": 0,
      "retweet_count": 10
    },
    "referenced_tweets": [
      {
        "id": "2019095471814549867",
        "type": "retweeted"
      }
    ],
    "reply_settings": "everyone",
    "text": "RT @S_Hyoscine: 妈的一群傻逼没事对🐴斯克女儿哈什么气，人家是女生，还天天叫人家🐴斯克儿子，真就一点尊重都不会呗"
  },
  "includes": {
    "tweets": [
      {
        "article": {},
        "attachments": {},
        "author_id": "1684788633797287936",
        "conversation_id": "2019596504005333156",
        "created_at": "2026-02-06T02:18:23.000Z",
        "edit_controls": {
          "editable_until": "2026-02-06T03:18:23.000Z",
          "edits_remaining": 5,
          "is_edit_eligible": false
        },
        "edit_history_tweet_ids": [
          "2019596504005333156"
        ],
        "entities": {
          "mentions": [
            {
              "end": 14,
              "id": "1935176310663401472",
              "start": 3,
              "username": "S_Hyoscine"
            }
          ]
        },
        "geo": {},
        "id": "2019596504005333156",
        "lang": "zh",
        "note_tweet": {
          "entities": {}
        },
        "possibly_sensitive": false,
        "public_metrics": {
          "bookmark_count": 0,
          "impression_count": 0,
          "like_count": 0,
          "quote_count": 0,
          "reply_count": 0,
          "retweet_count": 10
        },
        "referenced_tweets": [
          {
            "id": "2019095471814549867",
            "type": "retweeted"
          }
        ],
        "reply_settings": "everyone",
        "text": "RT @S_Hyoscine: 妈的一群傻逼没事对🐴斯克女儿哈什么气，人家是女生，还天天叫人家🐴斯克儿子，真就一点尊重都不会呗"
      },
      {
        "article": {},
        "attachments": {},
        "author_id": "1935176310663401472",
        "conversation_id": "2019095471814549867",
        "created_at": "2026-02-04T17:07:28.000Z",
        "edit_controls": {
          "editable_until": "2026-02-04T18:07:28.000Z",
          "edits_remaining": 5,
          "is_edit_eligible": true
        },
        "edit_history_tweet_ids": [
          "2019095471814549867"
        ],
        "entities": {},
        "geo": {},
        "id": "2019095471814549867",
        "lang": "zh",
        "note_tweet": {
          "entities": {}
        },
        "possibly_sensitive": false,
        "public_metrics": {
          "bookmark_count": 5,
          "impression_count": 16891,
          "like_count": 250,
          "quote_count": 2,
          "reply_count": 17,
          "retweet_count": 10
        },
        "reply_settings": "everyone",
        "text": "妈的一群傻逼没事对🐴斯克女儿哈什么气，人家是女生，还天天叫人家🐴斯克儿子，真就一点尊重都不会呗"
      }
    ],
    "users": [
      {
        "created_at": "2023-07-28T04:51:35.000Z",
        "derived": {
          "locations": [
            {
              "country_code": "TW",
              "full_name": "Taiwan (Province of China)",
              "geo": {
                "coordinates": [
                  121.0,
                  24.0
                ],
                "type": "Point"
              }
            }
          ]
        },
        "description": "🌌 | 🩵🩷🏳️‍⚧️ | mtf | 跨跨帮助跨跨 | 提问箱📦https://t.co/TOvX6zqP3L",
        "entities": {
          "description": {
            "urls": [
              {
                "display_url": "ngl.link/muoujiang_",
                "end": 56,
                "expanded_url": "https://ngl.link/muoujiang_",
                "start": 33,
                "url": "https://t.co/TOvX6zqP3L"
              }
            ]
          }
        },
        "id": "1684788633797287936",
        "location": "Taiwan",
        "name": "沫柠",
        "pinned_tweet_id": "1927365238833250356",
        "profile_image_url": "https://pbs.twimg.com/profile_images/2009681959396794368/z-ltr1zS_normal.jpg",
        "protected": false,
        "public_metrics": {
          "followers_count": 26432,
          "following_count": 10940,
          "like_count": 84964,
          "listed_count": 102,
          "media_count": 4695,
          "tweet_count": 15965
        },
        "username": "Moningmeng",
        "verified": false
      },
      {
        "created_at": "2025-06-18T03:23:09.000Z",
        "description": "07年跨妹//退役jk//陪聊门槛50抽象苹果粉//自由万岁//福利姬药娘//@hood438371无能的妻子//生产日期：07.03.22//知不可乎骤得，托遗响于悲风",
        "entities": {
          "description": {
            "mentions": [
              {
                "end": 50,
                "start": 39,
                "username": "hood438371"
              }
            ]
          }
        },
        "id": "1935176310663401472",
        "location": "三里屯水果批发市场",
        "name": "春雪狐与东莨🍥",
        "pinned_tweet_id": "2016068038773375401",
        "profile_image_url": "https://pbs.twimg.com/profile_images/2005380683292983296/Iictc7oI_normal.jpg",
        "protected": false,
        "public_metrics": {
          "followers_count": 1033,
          "following_count": 845,
          "like_count": 22286,
          "listed_count": 2,
          "media_count": 292,
          "tweet_count": 5509
        },
        "username": "S_Hyoscine",
        "verified": true
      }
    ]
  }
}