{
  "data": {
    "article": {},
    "attachments": {},
    "author_id": "1684788633797287936",
    "conversation_id": "2060267221554024613",
    "created_at": "2026-05-29T07:49:18.000Z",
    "edit_controls": {
      "editable_until": "2026-05-29T08:49:18.000Z",
      "edits_remaining": 5,
      "is_edit_eligible": false
    },
    "edit_history_tweet_ids": [
      "2060267221554024613"
    ],
    "entities": {
      "mentions": [
        {
          "end": 15,
          "id": "1780369819310981120",
          "start": 3,
          "username": "520illusion"
        }
      ]
    },
    "geo": {},
    "id": "2060267221554024613",
    "lang": "zh",
    "note_tweet": {
      "entities": {}
    },
    "possibly_sensitive": false,
    "public_metrics": {
      "bookmark_count": 0,
      "impression_count": 0,
      "like_count": 0,
      "quote_count": 0,
      "reply_count": 0,
      "retweet_count": 0
    },
    "referenced_tweets": [
      {
        "id": "2060217148300251460",
        "type": "retweeted"
      }
    ],
    "reply_settings": "everyone",
    "text": "RT @520illusion: 这两周 38 会变成违禁词  请大家谨慎发言 不信谣不传谣 不要触及政治红线 遵守当地法律法规 作一个爱国遵纪守法的好公民"
  },
  "includes": {
    "tweets": [
      {
        "article": {},
        "attachments": {},
        "author_id": "1684788633797287936",
        "conversation_id": "2060267221554024613",
        "created_at": "2026-05-29T07:49:18.000Z",
        "edit_controls": {
          "editable_until": "2026-05-29T08:49:18.000Z",
          "edits_remaining": 5,
          "is_edit_eligible": false
        },
        "edit_history_tweet_ids": [
          "2060267221554024613"
        ],
        "entities": {
          "mentions": [
            {
              "end": 15,
              "id": "1780369819310981120",
              "start": 3,
              "username": "520illusion"
            }
          ]
        },
        "geo": {},
        "id": "2060267221554024613",
        "lang": "zh",
        "note_tweet": {
          "entities": {}
        },
        "possibly_sensitive": false,
        "public_metrics": {
          "bookmark_count": 0,
          "impression_count": 0,
          "like_count": 0,
          "quote_count": 0,
          "reply_count": 0,
          "retweet_count": 0
        },
        "referenced_tweets": [
          {
            "id": "2060217148300251460",
            "type": "retweeted"
          }
        ],
        "reply_settings": "everyone",
        "text": "RT @520illusion: 这两周 38 会变成违禁词  请大家谨慎发言 不信谣不传谣 不要触及政治红线 遵守当地法律法规 作一个爱国遵纪守法的好公民"
      },
      {
        "article": {},
        "attachments": {},
        "author_id": "1780369819310981120",
        "conversation_id": "2060217148300251460",
        "created_at": "2026-05-29T04:30:19.000Z",
        "edit_controls": {
          "editable_until": "2026-05-29T05:30:19.000Z",
          "edits_remaining": 5,
          "is_edit_eligible": true
        },
        "edit_history_tweet_ids": [
          "2060217148300251460"
        ],
        "entities": {},
        "geo": {},
        "id": "2060217148300251460",
        "lang": "zh",
        "note_tweet": {
          "entities": {}
        },
        "possibly_sensitive": false,
        "public_metrics": {
          "bookmark_count": 0,
          "impression_count": 190,
          "like_count": 5,
          "quote_count": 0,
          "reply_count": 2,
          "retweet_count": 0
        },
        "reply_settings": "everyone",
        "text": "这两周 38 会变成违禁词  请大家谨慎发言 不信谣不传谣 不要触及政治红线 遵守当地法律法规 作一个爱国遵纪守法的好公民"
      }
    ],
    "users": [
      {
        "created_at": "2023-07-28T04:51:35.000Z",
        "derived": {
          "locations": [
            {
              "country_code": "TW",
              "full_name": "Taiwan (Province of China)",
              "geo": {
                "coordinates": [
                  121.0,
                  24.0
                ],
                "type": "Point"
              }
            }
          ]
        },
        "description": "🏳️‍⚧️ | 提问箱📦https://t.co/TOvX6zqP3L",
        "entities": {
          "description": {
            "urls": [
              {
                "display_url": "ngl.link/muoujiang_",
                "end": 35,
                "expanded_url": "https://ngl.link/muoujiang_",
                "start": 12,
                "url": "https://t.co/TOvX6zqP3L"
              }
            ]
          }
        },
        "id": "1684788633797287936",
        "location": "Taiwan",
        "name": "沫柠",
        "pinned_tweet_id": "1927365238833250356",
        "profile_image_url": "https://pbs.twimg.com/profile_images/2056364445513990144/e8qLKD9t_normal.jpg",
        "protected": false,
        "public_metrics": {
          "followers_count": 27678,
          "following_count": 11079,
          "like_count": 89272,
          "listed_count": 102,
          "media_count": 5160,
          "tweet_count": 17456
        },
        "username": "Moningmeng",
        "verified": true
      },
      {
        "created_at": "2024-04-16T22:57:15.000Z",
        "description": "All in crypto | 08女高 | 请不要查我的成分 | 永远的南京城 | illusion | 我向神明祈祷 许你岁岁平安  | 故里蓝鸢",
        "entities": {
          "url": {
            "urls": [
              {
                "display_url": "t.me/lanyuan",
                "end": 23,
                "expanded_url": "http://t.me/lanyuan",
                "start": 0,
                "url": "https://t.co/ecnOMDHn8U"
              }
            ]
          }
        },
        "id": "1780369819310981120",
        "location": "浙江省宁波市轨道交通3号线中兴大桥南站A出口",
        "name": "ill",
        "pinned_tweet_id": "1879295666419286059",
        "profile_image_url": "https://pbs.twimg.com/profile_images/2028863680889372672/zT5FAaR9_normal.png",
        "protected": false,
        "public_metrics": {
          "followers_count": 4625,
          "following_count": 190,
          "like_count": 10410,
          "listed_count": 8,
          "media_count": 935,
          "tweet_count": 6051
        },
        "url": "https://t.co/ecnOMDHn8U",
        "username": "520illusion",
        "verified": true
      }
    ]
  }
}