{
  "data": {
    "article": {},
    "attachments": {},
    "author_id": "1684788633797287936",
    "conversation_id": "2077905306668114410",
    "created_at": "2026-07-16T23:56:45.000Z",
    "edit_controls": {
      "editable_until": "2026-07-17T00:56:45.000Z",
      "edits_remaining": 5,
      "is_edit_eligible": false
    },
    "edit_history_tweet_ids": [
      "2077905306668114410"
    ],
    "entities": {
      "mentions": [
        {
          "end": 15,
          "id": "2048693394226974720",
          "start": 3,
          "username": "CCA8798suki"
        }
      ]
    },
    "geo": {},
    "id": "2077905306668114410",
    "lang": "zh",
    "note_tweet": {
      "entities": {}
    },
    "possibly_sensitive": false,
    "public_metrics": {
      "bookmark_count": 0,
      "impression_count": 0,
      "like_count": 0,
      "quote_count": 0,
      "reply_count": 0,
      "retweet_count": 2
    },
    "referenced_tweets": [
      {
        "id": "2077398147698176172",
        "type": "retweeted"
      }
    ],
    "reply_settings": "everyone",
    "text": "RT @CCA8798suki: 以前拿药：你好你们家补有优惠吗\n现在拿药：老妈给我来粒补佳乐🤓"
  },
  "includes": {
    "tweets": [
      {
        "article": {},
        "attachments": {},
        "author_id": "1684788633797287936",
        "conversation_id": "2077905306668114410",
        "created_at": "2026-07-16T23:56:45.000Z",
        "edit_controls": {
          "editable_until": "2026-07-17T00:56:45.000Z",
          "edits_remaining": 5,
          "is_edit_eligible": false
        },
        "edit_history_tweet_ids": [
          "2077905306668114410"
        ],
        "entities": {
          "mentions": [
            {
              "end": 15,
              "id": "2048693394226974720",
              "start": 3,
              "username": "CCA8798suki"
            }
          ]
        },
        "geo": {},
        "id": "2077905306668114410",
        "lang": "zh",
        "note_tweet": {
          "entities": {}
        },
        "possibly_sensitive": false,
        "public_metrics": {
          "bookmark_count": 0,
          "impression_count": 0,
          "like_count": 0,
          "quote_count": 0,
          "reply_count": 0,
          "retweet_count": 2
        },
        "referenced_tweets": [
          {
            "id": "2077398147698176172",
            "type": "retweeted"
          }
        ],
        "reply_settings": "everyone",
        "text": "RT @CCA8798suki: 以前拿药：你好你们家补有优惠吗\n现在拿药：老妈给我来粒补佳乐🤓"
      },
      {
        "article": {},
        "attachments": {},
        "author_id": "2048693394226974720",
        "conversation_id": "2077398147698176172",
        "created_at": "2026-07-15T14:21:29.000Z",
        "edit_controls": {
          "editable_until": "2026-07-15T15:21:29.000Z",
          "edits_remaining": 5,
          "is_edit_eligible": true
        },
        "edit_history_tweet_ids": [
          "2077398147698176172"
        ],
        "entities": {},
        "geo": {},
        "id": "2077398147698176172",
        "lang": "zh",
        "note_tweet": {
          "entities": {}
        },
        "possibly_sensitive": false,
        "public_metrics": {
          "bookmark_count": 1,
          "impression_count": 5316,
          "like_count": 89,
          "quote_count": 0,
          "reply_count": 46,
          "retweet_count": 2
        },
        "reply_settings": "everyone",
        "text": "以前拿药：你好你们家补有优惠吗\n现在拿药：老妈给我来粒补佳乐🤓"
      }
    ],
    "users": [
      {
        "created_at": "2023-07-28T04:51:35.000Z",
        "derived": {
          "locations": [
            {
              "country_code": "TW",
              "full_name": "Taiwan (Province of China)",
              "geo": {
                "coordinates": [
                  121.0,
                  24.0
                ],
                "type": "Point"
              }
            }
          ]
        },
        "description": "🏳️‍⚧️ 小证 | 互fo请私信 | 谷歌粉丝 | 闺蜜 @maoxianACT | 提问箱📦https://t.co/tfhHbaQ0gW",
        "entities": {
          "description": {
            "mentions": [
              {
                "end": 41,
                "start": 30,
                "username": "maoxianACT"
              }
            ],
            "urls": [
              {
                "display_url": "ngl.link/moningmeng",
                "end": 71,
                "expanded_url": "https://ngl.link/moningmeng",
                "start": 48,
                "url": "https://t.co/tfhHbaQ0gW"
              }
            ]
          }
        },
        "id": "1684788633797287936",
        "location": "Taiwan",
        "name": "沫柠🍥",
        "pinned_tweet_id": "2077683099979382894",
        "profile_image_url": "https://pbs.twimg.com/profile_images/2075833712986714112/3j84SM6e_normal.jpg",
        "protected": false,
        "public_metrics": {
          "followers_count": 28357,
          "following_count": 11660,
          "like_count": 94688,
          "listed_count": 104,
          "media_count": 5431,
          "tweet_count": 18975
        },
        "url": "",
        "username": "Moningmeng",
        "verified": true
      },
      {
        "created_at": "2026-04-27T09:19:12.000Z",
        "description": "MTF/X🍥 | 小证正规含糖 | 年龄党+半家长党 出柜26.05.05 出厂:壹贰.零壹.零叁 | 166cm/43kg | 佛山 |  偏内向 玻璃心 双相中焦 ED GD OD(Once/Month) | 交通 科学 医学 杂圈迷 | Cpp Coder | 寻回前世互fo | 恨MSK\n前世@CCA8798",
        "entities": {
          "description": {
            "mentions": [
              {
                "end": 159,
                "start": 151,
                "username": "CCA8798"
              }
            ]
          },
          "url": {
            "urls": [
              {
                "display_url": "cca8798.com/about/",
                "end": 23,
                "expanded_url": "https://cca8798.com/about/",
                "start": 0,
                "url": "https://t.co/XVFvMmA9Qt"
              }
            ]
          }
        },
        "id": "2048693394226974720",
        "location": "安东星蜗牛第一票常交易矿业太空旅行无限公司",
        "name": "不会起名の捌拐玖捌🍥(二代目)",
        "pinned_tweet_id": "2076708376483110961",
        "profile_image_url": "https://pbs.twimg.com/profile_images/2059761684500336640/bvv_7t16_normal.jpg",
        "protected": false,
        "public_metrics": {
          "followers_count": 1153,
          "following_count": 1345,
          "like_count": 5232,
          "listed_count": 3,
          "media_count": 98,
          "tweet_count": 725
        },
        "url": "https://t.co/XVFvMmA9Qt",
        "username": "CCA8798suki",
        "verified": true
      }
    ]
  }
}