{
  "data": {
    "article": {},
    "attachments": {},
    "author_id": "1684788633797287936",
    "conversation_id": "2074865639060357206",
    "created_at": "2026-07-09T05:29:55.000Z",
    "edit_controls": {
      "editable_until": "2026-07-09T06:29:55.000Z",
      "edits_remaining": 5,
      "is_edit_eligible": false
    },
    "edit_history_tweet_ids": [
      "2075090048551424493"
    ],
    "entities": {
      "mentions": [
        {
          "end": 10,
          "id": "1244282246111973382",
          "start": 0,
          "username": "SR_Malaya"
        }
      ]
    },
    "geo": {},
    "id": "2075090048551424493",
    "in_reply_to_user_id": "1244282246111973382",
    "lang": "zh",
    "note_tweet": {
      "entities": {}
    },
    "possibly_sensitive": false,
    "public_metrics": {
      "bookmark_count": 0,
      "impression_count": 0,
      "like_count": 0,
      "quote_count": 0,
      "reply_count": 0,
      "retweet_count": 0
    },
    "referenced_tweets": [
      {
        "id": "2074874202470126078",
        "type": "replied_to"
      }
    ],
    "reply_settings": "everyone",
    "text": "@SR_Malaya 我觉得女权跨可以理解……"
  },
  "includes": {
    "tweets": [
      {
        "article": {},
        "attachments": {},
        "author_id": "1684788633797287936",
        "conversation_id": "2074865639060357206",
        "created_at": "2026-07-09T05:29:55.000Z",
        "edit_controls": {
          "editable_until": "2026-07-09T06:29:55.000Z",
          "edits_remaining": 5,
          "is_edit_eligible": false
        },
        "edit_history_tweet_ids": [
          "2075090048551424493"
        ],
        "entities": {
          "mentions": [
            {
              "end": 10,
              "id": "1244282246111973382",
              "start": 0,
              "username": "SR_Malaya"
            }
          ]
        },
        "geo": {},
        "id": "2075090048551424493",
        "in_reply_to_user_id": "1244282246111973382",
        "lang": "zh",
        "note_tweet": {
          "entities": {}
        },
        "possibly_sensitive": false,
        "public_metrics": {
          "bookmark_count": 0,
          "impression_count": 0,
          "like_count": 0,
          "quote_count": 0,
          "reply_count": 0,
          "retweet_count": 0
        },
        "referenced_tweets": [
          {
            "id": "2074874202470126078",
            "type": "replied_to"
          }
        ],
        "reply_settings": "everyone",
        "text": "@SR_Malaya 我觉得女权跨可以理解……"
      },
      {
        "article": {},
        "attachments": {},
        "author_id": "1244282246111973382",
        "conversation_id": "2074865639060357206",
        "created_at": "2026-07-08T15:12:13.000Z",
        "edit_controls": {
          "editable_until": "2026-07-08T16:12:13.000Z",
          "edits_remaining": 5,
          "is_edit_eligible": false
        },
        "edit_history_tweet_ids": [
          "2074874202470126078"
        ],
        "entities": {
          "mentions": [
            {
              "end": 11,
              "id": "1684788633797287936",
              "start": 0,
              "username": "Moningmeng"
            }
          ]
        },
        "geo": {},
        "id": "2074874202470126078",
        "in_reply_to_user_id": "1684788633797287936",
        "lang": "zh",
        "note_tweet": {
          "entities": {}
        },
        "possibly_sensitive": false,
        "public_metrics": {
          "bookmark_count": 0,
          "impression_count": 403,
          "like_count": 8,
          "quote_count": 0,
          "reply_count": 1,
          "retweet_count": 0
        },
        "referenced_tweets": [
          {
            "id": "2074865639060357206",
            "type": "replied_to"
          }
        ],
        "reply_settings": "everyone",
        "text": "@Moningmeng 还有女权跨呢"
      }
    ],
    "users": [
      {
        "created_at": "2023-07-28T04:51:35.000Z",
        "derived": {
          "locations": [
            {
              "country_code": "TW",
              "full_name": "Taiwan (Province of China)",
              "geo": {
                "coordinates": [
                  121.0,
                  24.0
                ],
                "type": "Point"
              }
            }
          ]
        },
        "description": "🏳️‍⚧️ 小证 | 互fo请私信 | 闺蜜 @maoxianACT | 提问箱📦https://t.co/tfhHbaQ0gW",
        "entities": {
          "description": {
            "mentions": [
              {
                "end": 34,
                "start": 23,
                "username": "maoxianACT"
              }
            ],
            "urls": [
              {
                "display_url": "ngl.link/moningmeng",
                "end": 64,
                "expanded_url": "https://ngl.link/moningmeng",
                "start": 41,
                "url": "https://t.co/tfhHbaQ0gW"
              }
            ]
          }
        },
        "id": "1684788633797287936",
        "location": "Taiwan",
        "name": "沫柠🍥",
        "profile_image_url": "https://pbs.twimg.com/profile_images/2070463166337953792/xmL4_Gt1_normal.jpg",
        "protected": false,
        "public_metrics": {
          "followers_count": 28112,
          "following_count": 11495,
          "like_count": 93369,
          "listed_count": 104,
          "media_count": 5353,
          "tweet_count": 18614
        },
        "url": "",
        "username": "Moningmeng",
        "verified": true
      },
      {
        "created_at": "2020-03-29T15:16:38.000Z",
        "description": "开动脑筋",
        "id": "1244282246111973382",
        "name": "乱编瞎想",
        "pinned_tweet_id": "1987742663857311863",
        "profile_image_url": "https://pbs.twimg.com/profile_images/1987785156305055744/jlKFXN_C_normal.jpg",
        "protected": false,
        "public_metrics": {
          "followers_count": 8028,
          "following_count": 3590,
          "like_count": 5378,
          "listed_count": 43,
          "media_count": 1031,
          "tweet_count": 9434
        },
        "url": "",
        "username": "SR_Malaya",
        "verified": false
      }
    ]
  }
}