{
  "data": {
    "article": {},
    "attachments": {
      "media_keys": [
        "3_2059772764933025792"
      ],
      "media_source_tweet_id": [
        "2059772772637966664"
      ]
    },
    "author_id": "1684788633797287936",
    "conversation_id": "2059849356514410940",
    "created_at": "2026-05-28T04:08:51.000Z",
    "edit_controls": {
      "editable_until": "2026-05-28T05:08:51.000Z",
      "edits_remaining": 5,
      "is_edit_eligible": false
    },
    "edit_history_tweet_ids": [
      "2059849356514410940"
    ],
    "entities": {
      "mentions": [
        {
          "end": 16,
          "id": "1928705633135767600",
          "start": 3,
          "username": "PriseTwinkle"
        }
      ],
      "urls": [
        {
          "display_url": "pic.x.com/m2XimVFbRx",
          "end": 53,
          "expanded_url": "https://x.com/PriseTwinkle/status/2059772772637966664/photo/1",
          "media_key": "3_2059772764933025792",
          "start": 30,
          "url": "https://t.co/m2XimVFbRx"
        }
      ]
    },
    "geo": {},
    "id": "2059849356514410940",
    "lang": "zh",
    "note_tweet": {
      "entities": {}
    },
    "possibly_sensitive": false,
    "public_metrics": {
      "bookmark_count": 0,
      "impression_count": 0,
      "like_count": 0,
      "quote_count": 0,
      "reply_count": 0,
      "retweet_count": 0
    },
    "referenced_tweets": [
      {
        "id": "2059772772637966664",
        "type": "retweeted"
      }
    ],
    "reply_settings": "everyone",
    "text": "RT @PriseTwinkle: 为什么我也是涩推类型🤔 https://t.co/m2XimVFbRx"
  },
  "includes": {
    "media": [
      {
        "height": 799,
        "media_key": "3_2059772764933025792",
        "public_metrics": {},
        "type": "photo",
        "url": "https://pbs.twimg.com/media/HJXIaqPbcAAcA-5.jpg",
        "width": 1240
      }
    ],
    "tweets": [
      {
        "article": {},
        "attachments": {
          "media_keys": [
            "3_2059772764933025792"
          ],
          "media_source_tweet_id": [
            "2059772772637966664"
          ]
        },
        "author_id": "1684788633797287936",
        "conversation_id": "2059849356514410940",
        "created_at": "2026-05-28T04:08:51.000Z",
        "edit_controls": {
          "editable_until": "2026-05-28T05:08:51.000Z",
          "edits_remaining": 5,
          "is_edit_eligible": false
        },
        "edit_history_tweet_ids": [
          "2059849356514410940"
        ],
        "entities": {
          "mentions": [
            {
              "end": 16,
              "id": "1928705633135767600",
              "start": 3,
              "username": "PriseTwinkle"
            }
          ],
          "urls": [
            {
              "display_url": "pic.x.com/m2XimVFbRx",
              "end": 53,
              "expanded_url": "https://x.com/PriseTwinkle/status/2059772772637966664/photo/1",
              "media_key": "3_2059772764933025792",
              "start": 30,
              "url": "https://t.co/m2XimVFbRx"
            }
          ]
        },
        "geo": {},
        "id": "2059849356514410940",
        "lang": "zh",
        "note_tweet": {
          "entities": {}
        },
        "possibly_sensitive": false,
        "public_metrics": {
          "bookmark_count": 0,
          "impression_count": 0,
          "like_count": 0,
          "quote_count": 0,
          "reply_count": 0,
          "retweet_count": 0
        },
        "referenced_tweets": [
          {
            "id": "2059772772637966664",
            "type": "retweeted"
          }
        ],
        "reply_settings": "everyone",
        "text": "RT @PriseTwinkle: 为什么我也是涩推类型🤔 https://t.co/m2XimVFbRx"
      },
      {
        "article": {},
        "attachments": {
          "media_keys": [
            "3_2059772764933025792"
          ]
        },
        "author_id": "1928705633135767600",
        "conversation_id": "2059772772637966664",
        "created_at": "2026-05-27T23:04:32.000Z",
        "edit_controls": {
          "editable_until": "2026-05-28T00:04:32.000Z",
          "edits_remaining": 5,
          "is_edit_eligible": true
        },
        "edit_history_tweet_ids": [
          "2059772772637966664"
        ],
        "entities": {
          "urls": [
            {
              "display_url": "pic.x.com/m2XimVFbRx",
              "end": 35,
              "expanded_url": "https://x.com/PriseTwinkle/status/2059772772637966664/photo/1",
              "media_key": "3_2059772764933025792",
              "start": 12,
              "url": "https://t.co/m2XimVFbRx"
            },
            {
              "display_url": "x.com/xynMTFxyn/stat…",
              "end": 59,
              "expanded_url": "https://twitter.com/xynMTFxyn/status/2059757889850601629",
              "start": 36,
              "url": "https://t.co/BtWdd44sS1"
            }
          ]
        },
        "geo": {},
        "id": "2059772772637966664",
        "lang": "zh",
        "note_tweet": {
          "entities": {}
        },
        "possibly_sensitive": false,
        "public_metrics": {
          "bookmark_count": 0,
          "impression_count": 466,
          "like_count": 15,
          "quote_count": 0,
          "reply_count": 1,
          "retweet_count": 0
        },
        "referenced_tweets": [
          {
            "id": "2059757889850601629",
            "type": "quoted"
          }
        ],
        "reply_settings": "everyone",
        "text": "为什么我也是涩推类型🤔 https://t.co/m2XimVFbRx https://t.co/BtWdd44sS1"
      }
    ],
    "users": [
      {
        "created_at": "2023-07-28T04:51:35.000Z",
        "derived": {
          "locations": [
            {
              "country_code": "TW",
              "full_name": "Taiwan (Province of China)",
              "geo": {
                "coordinates": [
                  121.0,
                  24.0
                ],
                "type": "Point"
              }
            }
          ]
        },
        "description": "🏳️‍⚧️ | 提问箱📦https://t.co/TOvX6zqP3L",
        "entities": {
          "description": {
            "urls": [
              {
                "display_url": "ngl.link/muoujiang_",
                "end": 35,
                "expanded_url": "https://ngl.link/muoujiang_",
                "start": 12,
                "url": "https://t.co/TOvX6zqP3L"
              }
            ]
          }
        },
        "id": "1684788633797287936",
        "location": "Taiwan",
        "name": "沫柠",
        "pinned_tweet_id": "1927365238833250356",
        "profile_image_url": "https://pbs.twimg.com/profile_images/2056364445513990144/e8qLKD9t_normal.jpg",
        "protected": false,
        "public_metrics": {
          "followers_count": 27651,
          "following_count": 11073,
          "like_count": 88984,
          "listed_count": 102,
          "media_count": 5157,
          "tweet_count": 17404
        },
        "username": "Moningmeng",
        "verified": true
      },
      {
        "created_at": "2025-05-31T06:51:03.000Z",
        "description": "13岁 7年级 初二生 泛性恋？跨圈最小的? \n无证小药娘🍥2026.4.7 MTF\n从小想做个女孩子-炸柜：5.2/继续深柜ing\n喜欢折腾电脑和会一点编程\n分享Hrt日常- 💊&🔪\n喜欢我的话点个关注吧🥺 求求你了~\n@TeamRain_2024 | http://t.co/yw95e9HjhX",
        "entities": {
          "description": {
            "mentions": [
              {
                "end": 125,
                "start": 111,
                "username": "TeamRain_2024"
              }
            ],
            "urls": [
              {
                "display_url": "NGL.Link/prisetwinkle",
                "end": 150,
                "expanded_url": "http://NGL.Link/prisetwinkle",
                "start": 128,
                "url": "http://t.co/yw95e9HjhX"
              }
            ]
          },
          "url": {
            "urls": [
              {
                "display_url": "t.me/PriseTwinkle",
                "end": 23,
                "expanded_url": "http://t.me/PriseTwinkle",
                "start": 0,
                "url": "https://t.co/vVpfNV6DFI"
              }
            ]
          }
        },
        "id": "1928705633135767600",
        "location": "湖北潜江",
        "name": "芸光酱𝕻𝖗𝖎𝖘𝖊𝕿𝖜𝖎𝖓𝖐𝖑𝖊 🍥🏳️‍⚧️",
        "pinned_tweet_id": "2041475934608380289",
        "profile_image_url": "https://pbs.twimg.com/profile_images/2059287173812412416/vAimrkvi_normal.jpg",
        "protected": false,
        "public_metrics": {
          "followers_count": 1204,
          "following_count": 7,
          "like_count": 2020,
          "listed_count": 5,
          "media_count": 103,
          "tweet_count": 748
        },
        "url": "https://t.co/vVpfNV6DFI",
        "username": "PriseTwinkle",
        "verified": true
      }
    ]
  }
}