{
  "data": {
    "article": {},
    "attachments": {
      "media_keys": [
        "3_2059007963688235009",
        "3_2059007987641966592"
      ],
      "media_source_tweet_id": [
        "2059008337853755785",
        "2059008337853755785"
      ]
    },
    "author_id": "1684788633797287936",
    "conversation_id": "2059124173923074400",
    "created_at": "2026-05-26T04:07:14.000Z",
    "edit_controls": {
      "editable_until": "2026-05-26T05:07:14.000Z",
      "edits_remaining": 5,
      "is_edit_eligible": false
    },
    "edit_history_tweet_ids": [
      "2059124173923074400"
    ],
    "entities": {
      "mentions": [
        {
          "end": 16,
          "id": "1993455710274043905",
          "start": 3,
          "username": "satireorcry1"
        }
      ],
      "urls": [
        {
          "display_url": "pic.x.com/76suWTEj9E",
          "end": 84,
          "expanded_url": "https://x.com/satireorcry1/status/2059008337853755785/photo/1",
          "media_key": "3_2059007963688235009",
          "start": 61,
          "url": "https://t.co/76suWTEj9E"
        },
        {
          "display_url": "pic.x.com/76suWTEj9E",
          "end": 84,
          "expanded_url": "https://x.com/satireorcry1/status/2059008337853755785/photo/1",
          "media_key": "3_2059007987641966592",
          "start": 61,
          "url": "https://t.co/76suWTEj9E"
        }
      ]
    },
    "geo": {},
    "id": "2059124173923074400",
    "lang": "zh",
    "note_tweet": {
      "entities": {}
    },
    "possibly_sensitive": false,
    "public_metrics": {
      "bookmark_count": 0,
      "impression_count": 0,
      "like_count": 0,
      "quote_count": 0,
      "reply_count": 0,
      "retweet_count": 1
    },
    "referenced_tweets": [
      {
        "id": "2059008337853755785",
        "type": "retweeted"
      }
    ],
    "reply_settings": "everyone",
    "text": "RT @satireorcry1: 各位翻墙一定要保护好账号隐私!\n网友进去被教育了，手机也打开拿去翻了，全程手心全是汗 https://t.co/76suWTEj9E"
  },
  "includes": {
    "media": [
      {
        "height": 2556,
        "media_key": "3_2059007963688235009",
        "public_metrics": {},
        "type": "photo",
        "url": "https://pbs.twimg.com/media/HJMQ1XlWcAElcrS.jpg",
        "width": 1179
      },
      {
        "height": 2556,
        "media_key": "3_2059007987641966592",
        "public_metrics": {},
        "type": "photo",
        "url": "https://pbs.twimg.com/media/HJMQ2w0XYAAyKc0.jpg",
        "width": 1179
      }
    ],
    "tweets": [
      {
        "article": {},
        "attachments": {
          "media_keys": [
            "3_2059007963688235009",
            "3_2059007987641966592"
          ],
          "media_source_tweet_id": [
            "2059008337853755785",
            "2059008337853755785"
          ]
        },
        "author_id": "1684788633797287936",
        "conversation_id": "2059124173923074400",
        "created_at": "2026-05-26T04:07:14.000Z",
        "edit_controls": {
          "editable_until": "2026-05-26T05:07:14.000Z",
          "edits_remaining": 5,
          "is_edit_eligible": false
        },
        "edit_history_tweet_ids": [
          "2059124173923074400"
        ],
        "entities": {
          "mentions": [
            {
              "end": 16,
              "id": "1993455710274043905",
              "start": 3,
              "username": "satireorcry1"
            }
          ],
          "urls": [
            {
              "display_url": "pic.x.com/76suWTEj9E",
              "end": 84,
              "expanded_url": "https://x.com/satireorcry1/status/2059008337853755785/photo/1",
              "media_key": "3_2059007963688235009",
              "start": 61,
              "url": "https://t.co/76suWTEj9E"
            },
            {
              "display_url": "pic.x.com/76suWTEj9E",
              "end": 84,
              "expanded_url": "https://x.com/satireorcry1/status/2059008337853755785/photo/1",
              "media_key": "3_2059007987641966592",
              "start": 61,
              "url": "https://t.co/76suWTEj9E"
            }
          ]
        },
        "geo": {},
        "id": "2059124173923074400",
        "lang": "zh",
        "note_tweet": {
          "entities": {}
        },
        "possibly_sensitive": false,
        "public_metrics": {
          "bookmark_count": 0,
          "impression_count": 0,
          "like_count": 0,
          "quote_count": 0,
          "reply_count": 0,
          "retweet_count": 1
        },
        "referenced_tweets": [
          {
            "id": "2059008337853755785",
            "type": "retweeted"
          }
        ],
        "reply_settings": "everyone",
        "text": "RT @satireorcry1: 各位翻墙一定要保护好账号隐私!\n网友进去被教育了，手机也打开拿去翻了，全程手心全是汗 https://t.co/76suWTEj9E"
      },
      {
        "article": {},
        "attachments": {
          "media_keys": [
            "3_2059007963688235009",
            "3_2059007987641966592"
          ]
        },
        "author_id": "1993455710274043905",
        "conversation_id": "2059008337853755785",
        "created_at": "2026-05-25T20:26:56.000Z",
        "edit_controls": {
          "editable_until": "2026-05-25T21:26:56.000Z",
          "edits_remaining": 5,
          "is_edit_eligible": true
        },
        "edit_history_tweet_ids": [
          "2059008337853755785"
        ],
        "entities": {
          "urls": [
            {
              "display_url": "pic.x.com/76suWTEj9E",
              "end": 66,
              "expanded_url": "https://x.com/satireorcry1/status/2059008337853755785/photo/1",
              "media_key": "3_2059007963688235009",
              "start": 43,
              "url": "https://t.co/76suWTEj9E"
            },
            {
              "display_url": "pic.x.com/76suWTEj9E",
              "end": 66,
              "expanded_url": "https://x.com/satireorcry1/status/2059008337853755785/photo/1",
              "media_key": "3_2059007987641966592",
              "start": 43,
              "url": "https://t.co/76suWTEj9E"
            }
          ]
        },
        "geo": {},
        "id": "2059008337853755785",
        "lang": "zh",
        "note_tweet": {
          "entities": {}
        },
        "possibly_sensitive": false,
        "public_metrics": {
          "bookmark_count": 13,
          "impression_count": 11081,
          "like_count": 62,
          "quote_count": 0,
          "reply_count": 8,
          "retweet_count": 1
        },
        "reply_settings": "everyone",
        "text": "各位翻墙一定要保护好账号隐私!\n网友进去被教育了，手机也打开拿去翻了，全程手心全是汗 https://t.co/76suWTEj9E"
      }
    ],
    "users": [
      {
        "created_at": "2023-07-28T04:51:35.000Z",
        "derived": {
          "locations": [
            {
              "country_code": "TW",
              "full_name": "Taiwan (Province of China)",
              "geo": {
                "coordinates": [
                  121.0,
                  24.0
                ],
                "type": "Point"
              }
            }
          ]
        },
        "description": "🏳️‍⚧️ | 提问箱📦https://t.co/TOvX6zqP3L",
        "entities": {
          "description": {
            "urls": [
              {
                "display_url": "ngl.link/muoujiang_",
                "end": 35,
                "expanded_url": "https://ngl.link/muoujiang_",
                "start": 12,
                "url": "https://t.co/TOvX6zqP3L"
              }
            ]
          }
        },
        "id": "1684788633797287936",
        "location": "Taiwan",
        "name": "沫柠",
        "pinned_tweet_id": "1927365238833250356",
        "profile_image_url": "https://pbs.twimg.com/profile_images/2056364445513990144/e8qLKD9t_normal.jpg",
        "protected": false,
        "public_metrics": {
          "followers_count": 27629,
          "following_count": 11058,
          "like_count": 88813,
          "listed_count": 102,
          "media_count": 5145,
          "tweet_count": 17345
        },
        "username": "Moningmeng",
        "verified": true
      },
      {
        "created_at": "2025-11-25T23:04:21.000Z",
        "description": "专注梗图制作20年。 Professional meme maker for 20 years.\n\n欢迎商业洽谈，请用邮箱联系：furinana.x.com@gmail.com",
        "entities": {
          "url": {
            "urls": [
              {
                "display_url": "t.me/furinanaX",
                "end": 23,
                "expanded_url": "https://t.me/furinanaX",
                "start": 0,
                "url": "https://t.co/EYxWvog37z"
              }
            ]
          }
        },
        "id": "1993455710274043905",
        "location": "12 Millbank, London, SW1P 4QE",
        "name": "芙宁娜娜💙Furinana (王者归来版）",
        "pinned_tweet_id": "2038163914714660961",
        "profile_image_url": "https://pbs.twimg.com/profile_images/2005923449881972736/kaKnegOz_normal.png",
        "protected": false,
        "public_metrics": {
          "followers_count": 31572,
          "following_count": 1616,
          "like_count": 18945,
          "listed_count": 74,
          "media_count": 4154,
          "tweet_count": 5804
        },
        "url": "https://t.co/EYxWvog37z",
        "username": "satireorcry1",
        "verified": true
      }
    ]
  }
}